tang_ws2812/ws1228_driver.vhd
library IEEE;
use IEEE.STD_LOGIC_1164.ALL;
use IEEE.NUMERIC_STD.ALL;


entity ws1228_driver is
    Port ( drv_clk : in  STD_LOGIC;
           r : in  STD_LOGIC_VECTOR (7 downto 0);
           g : in  STD_LOGIC_VECTOR (7 downto 0);
           b : in  STD_LOGIC_VECTOR (7 downto 0);
	   enable: in STD_LOGIC;
	   output: out STD_LOGIC := '0';
	   done: out STD_LOGIC := '0' );
end ws1228_driver;

architecture ws1228_driver_arch of ws1228_driver is

begin
	process(drv_clk, enable)
	variable txdata: std_logic_vector(23 downto 0) := "000000000000000000000000";
	variable index: natural range 0 to 23 := 0;
	variable transmit: std_logic := '0';
	begin
	if rising_edge(enable) then
		txdata(23 downto 16) := r;
		txdata(15 downto 8) := g;
		txdata(7 downto 0) := b;
		index := 0;
		transmit := '1';
		done <= '0';
	end if;
	if rising_edge(drv_clk) then
		if transmit = '1' then 
			output <= txdata(index);	
			if index = 23 then
				done <= '1';
			else
				index := index + 1;
			end if;
		end if;
	end if;

	end process;
	

end ws1228_driver_arch;

tang_ws2812/ws1228_driver_tb.vhd
library IEEE;
use IEEE.STD_LOGIC_1164.ALL;
use IEEE.NUMERIC_STD.ALL;

entity ws1228_driver_tb is
end ws1228_driver_tb;

architecture ws1228_driver_arch_tb of ws1228_driver_tb is
component ws1228_driver is port (
	drv_clk : in  STD_LOGIC;
	r : in  STD_LOGIC_VECTOR (7 downto 0);
	g : in  STD_LOGIC_VECTOR (7 downto 0);
	b : in  STD_LOGIC_VECTOR (7 downto 0);
	enable: in STD_LOGIC;
	output: out STD_LOGIC;
	done: out STD_LOGIC	);
end component;

--for uut: ws1228_driver use entity work.ws1228_driver;

signal clk:  STD_LOGIC := '1';
signal r_reg: STD_LOGIC_VECTOR (7 downto 0) := (others => '0');
signal g_reg: STD_LOGIC_VECTOR (7 downto 0) := (others => '0');
signal b_reg: STD_LOGIC_VECTOR (7 downto 0) := (others => '0');
signal en:  STD_LOGIC := '0';
signal outd:  STD_LOGIC;
signal don:  STD_LOGIC;
signal sym_stop: STD_LOGIC := '0';
constant clk_period : time := 20 ns;

begin
uut: ws1228_driver port map ( 
	drv_clk => clk,
	r => r_reg,
	g => g_reg,
	b => b_reg,
	enable => en,
	output => outd,
	done => don
);

clk_process : process
begin
	clk <= '0';
	wait for clk_period/2;
	clk <= '1';
	wait for clk_period/2;
	if sym_stop = '1' then
		wait;
	end if;
end process;

stim_process : process
begin
	wait for 30 ns;
	r_reg <= x"0A";
	g_reg <= x"0B";
	b_reg <= x"0C";
	en <= '1';
	wait for 100 ns;
	wait for 500 ns;
	report "end of test" severity note;
	sym_stop <= '1';
	wait;
end process;


end;

tang_ws2812/ws1228_driver.vcd
$date
  Sun Jul 28 00:03:44 2024
$end
$version
  GHDL v0
$end
$timescale
  1 fs
$end
$scope module standard $end
$upscope $end
$scope module std_logic_1164 $end
$upscope $end
$scope module numeric_std $end
$upscope $end
$scope module ws1228_driver_tb $end
$var reg 1 ! clk $end
$var reg 8 " r_reg[7:0] $end
$var reg 8 # g_reg[7:0] $end
$var reg 8 $ b_reg[7:0] $end
$var reg 1 % en $end
$var reg 1 & outd $end
$var reg 1 ' don $end
$var reg 1 ( sym_stop $end
$scope module uut $end
$var reg 1 ) drv_clk $end
$var reg 8 * r[7:0] $end
$var reg 8 + g[7:0] $end
$var reg 8 , b[7:0] $end
$var reg 1 - enable $end
$var reg 1 . output $end
$var reg 1 / done $end
$upscope $end
$upscope $end
$enddefinitions $end
#0
0!
b00000000 "
b00000000 #
b00000000 $
0%
0&
0'
0(
0)
b00000000 *
b00000000 +
b00000000 ,
0-
0.
0/
#10000000
1!
1)
#20000000
0!
0)
#30000000
1!
b00001010 "
b00001011 #
b00001100 $
1%
1)
b00001010 *
b00001011 +
b00001100 ,
1-
#40000000
0!
0)
#50000000
1!
1)
#60000000
0!
0)
#70000000
1!
1&
1)
1.
#80000000
0!
0)
#90000000
1!
1)
#100000000
0!
0)
#110000000
1!
0&
1)
0.
#120000000
0!
0)
#130000000
1!
1)
#140000000
0!
0)
#150000000
1!
1)
#160000000
0!
0)
#170000000
1!
1)
#180000000
0!
0)
#190000000
1!
1&
1)
1.
#200000000
0!
0)
#210000000
1!
1)
#220000000
0!
0)
#230000000
1!
0&
1)
0.
#240000000
0!
0)
#250000000
1!
1&
1)
1.
#260000000
0!
0)
#270000000
1!
0&
1)
0.
#280000000
0!
0)
#290000000
1!
1)
#300000000
0!
0)
#310000000
1!
1)
#320000000
0!
0)
#330000000
1!
1)
#340000000
0!
0)
#350000000
1!
1)
#360000000
0!
0)
#370000000
1!
1&
1)
1.
#380000000
0!
0)
#390000000
1!
0&
1)
0.
#400000000
0!
0)
#410000000
1!
1&
1)
1.
#420000000
0!
0)
#430000000
1!
0&
1)
0.
#440000000
0!
0)
#450000000
1!
1)
#460000000
0!
0)
#470000000
1!
1)
#480000000
0!
0)
#490000000
1!
1'
1)
1/
#500000000
0!
0)
#510000000
1!
1)
#520000000
0!
0)
#530000000
1!
1)
#540000000
0!
0)
#550000000
1!
1)
#560000000
0!
0)
#570000000
1!
1)
#580000000
0!
0)
#590000000
1!
1)
#600000000
0!
0)
#610000000
1!
1)
#620000000
0!
0)
#630000000
1!
1(
1)
